socratic/__init__.py
socratic/__main__.py
socratic/cli.py
socratic/compose.py
socratic/constants.py
socratic/create.py
socratic/ingest.py
socratic/io_utils.py
socratic/synth.py
socratic_cli-0.0.1.dist-info/licenses/LICENSE
socratic_cli-0.0.1.dist-info/METADATA
socratic_cli-0.0.1.dist-info/WHEEL
socratic_cli-0.0.1.dist-info/entry_points.txt
socratic_cli-0.0.1.dist-info/top_level.txt
socratic_cli-0.0.1.dist-info/RECORD
