Metadata-Version: 2.4
Name: socratic-cli
Version: 0.0.1
Summary: Socratic: Automated Knowledge Synthesis for Vertical LLM Agents
Author-email: Kevin Song <kevinsong981@gmail.com>
License-Expression: Apache-2.0
Project-URL: Homepage, https://github.com/kevins981/Socratic
Project-URL: Issues, https://github.com/kevins981/Socratic/issues
Classifier: Programming Language :: Python :: 3
Requires-Python: >=3.10
License-File: LICENSE
Requires-Dist: openai>=1.0.0
Requires-Dist: inquirerpy>=0.3.4
Dynamic: license-file
